Metadata-Version: 2.1
Name: requestsping
Version: 1.1
Summary: A tutorial for creating pip packages.
Home-page: https://github.com/MichaelKim0407/tutorial-pip-package
Author: Michael Kim
Author-email: mkim0407@gmail.com
Classifier: Intended Audience :: Developers
Classifier: Programming Language :: Python
Classifier: Programming Language :: Python :: 3
Provides-Extra: math
Provides-Extra: bin
Provides-Extra: test
Provides-Extra: dev
Provides-Extra: ci
